tree_sitter_graphql/__init__.py
tree_sitter_graphql/__init__.pyi
tree_sitter_graphql/_binding.abi3.so
tree_sitter_graphql/binding.c
tree_sitter_graphql/py.typed
tree_sitter_graphql-0.1.0.dist-info/licenses/LICENSE
tree_sitter_graphql-0.1.0.dist-info/METADATA
tree_sitter_graphql-0.1.0.dist-info/WHEEL
tree_sitter_graphql-0.1.0.dist-info/top_level.txt
tree_sitter_graphql-0.1.0.dist-info/RECORD
