Metadata-Version: 2.4
Name: tree-sitter-graphql
Version: 0.1.0
Summary: GraphQL grammar for tree-sitter
Author-email: Joohwan Oh <joohwan.oh@outlook.com>
License: MIT
Project-URL: Homepage, https://github.com/joowani/tree-sitter-graphql
Keywords: incremental,parsing,tree-sitter,graphql
Classifier: Intended Audience :: Developers
Classifier: Topic :: Software Development :: Compilers
Classifier: Topic :: Text Processing :: Linguistic
Classifier: Typing :: Typed
Requires-Python: >=3.10
License-File: LICENSE
Provides-Extra: core
Requires-Dist: tree-sitter~=0.24; extra == "core"
Dynamic: license-file
